arq_admin/__init__.py
arq_admin/apps.py
arq_admin/compat.py
arq_admin/job.py
arq_admin/py.typed
arq_admin/queue.py
arq_admin/settings.py
arq_admin/urls.py
arq_admin/views.py
arq_admin/templates/admin/base.html
arq_admin/templates/arq_admin/job_abort.html
arq_admin/templates/arq_admin/job_detail.html
arq_admin/templates/arq_admin/jobs.html
arq_admin/templates/arq_admin/queues.html
arq_django_admin-0.3.4.dist-info/licenses/LICENSE
arq_django_admin-0.3.4.dist-info/METADATA
arq_django_admin-0.3.4.dist-info/WHEEL
arq_django_admin-0.3.4.dist-info/top_level.txt
arq_django_admin-0.3.4.dist-info/zip-safe
arq_django_admin-0.3.4.dist-info/RECORD
